bothub-0.1.30.dist-info/METADATA
bothub-0.1.30.dist-info/RECORD
bothub-0.1.30.dist-info/WHEEL
bothub-0.1.30.dist-info/top_level.txt
bothub_client/__init__.py
bothub_client/bot.py
bothub_client/clients.py
bothub_client/decorators.py
bothub_client/dispatcher.py
bothub_client/intent.py
bothub_client/messages.py
bothub_client/transports.py
bothub_client/utils.py
tests/__init__.py
tests/test_bot.py
tests/test_client.py
tests/test_dispatcher.py
tests/test_intent.py
tests/test_messages.py
tests/test_nlu_client.py
tests/test_storage_client.py
tests/test_transports.py
tests/test_utils.py
tests/testutils.py
