Metadata-Version: 2.1
Name: bothub
Version: 0.1.30
Summary: Build serverless chatbot on BotHub.Studio
Home-page: https://github.com/bothub-studio/bothub-sdk-python
Author: Jeongsoo Park
Author-email: jeongsoo.park@bothub.studio
License: AGPL v3
Keywords: bothub serverless chatbot framework
Platform: UNKNOWN
Classifier: Development Status :: 3 - Alpha
Classifier: Intended Audience :: Developers
Classifier: Operating System :: OS Independent
Classifier: License :: OSI Approved :: GNU Affero General Public License v3 or later (AGPLv3+)
Classifier: Programming Language :: Python
Classifier: Programming Language :: Python :: 2
Classifier: Programming Language :: Python :: 3
Classifier: Topic :: Communications :: Chat
Classifier: Topic :: Software Development :: Libraries :: Application Frameworks
Classifier: Topic :: Utilities
Requires-Dist: requests
Requires-Dist: zmq
Requires-Dist: pyaml
